DecoKit/DecoKit.py
DecoKit/__init__.py
decokit-1.0.0.dist-info/licenses/LICENSE
decokit-1.0.0.dist-info/METADATA
decokit-1.0.0.dist-info/WHEEL
decokit-1.0.0.dist-info/top_level.txt
decokit-1.0.0.dist-info/RECORD
